{
    "Name": "TryLevel_GiftMachine",
    "BGM": "Loonboon",
    "Description": "{UserName}的礼盒机",
    "Event": {
        "EventInit": [],
        "EventReady": [],
        "EventStart": []
    },
    "HomeWorld": "NOONE",
    "LevelName": "礼盒机",
    "LevelNumber": 1,
    "Map": "FrontlawnCold",
    "PacketBank": {
        "LimitGridPlantNum": -1,
        "Method": "PRESET",
        "Type": "GeneralPlant",
        "Value": [
            {
                "PacketName": "PlantGiftMachine"
            },
            {
                "PacketName": "PlantSunMine"
            },
            {
                "PacketName": "PlantSunShroom"
            },
            {
                "PacketName": "PlantImitaterW"
            },
            {
                "PacketName": "PlantSnowBlover"
            },
            {
                "PacketName": "PlantSnowShroom"
            },
            {
                "PacketName": "PlantBYWZ"
            },
            {
                "PacketName": "PlantBYWZ"
            },
            {
                "PacketName": "PlantBYWZ"
            },
            {
                "PacketName": "PlantMarigold"
            },
            {
                "PacketName": "PlantMarigold"
            },
            {
                "PacketName": "PlantMarigold"
            },
            {
                "PacketName": "PlantMariGoldMagnet"
            }
        ]
    },
    "PreSpawn": {
        "Packet": [
            {
                "GridPos": [
                    5,
                    3
                ],
                "Name": "PlantGiftMachine"
            }
        ]
    },
    "Reward": {
        "RewardFirst": "2000",
        "RewardType": "COIN"
    },
    "SunManager": {
        "Begin": 500,
        "MovingMethod": "LAND",
        "Open": false,
        "SpawnInterval": 12.0,
        "SpawnNum": 50
    },
    "Talk": "",
    "Tutorial": "",
    "WaveManager": {
        "BeginCol": 1.0,
        "Dynamic": [
            {},
            {},
            {},
            {},
            {},
            {},
            {}
        ],
        "FlagWaveInterval": 8,
        "FlagZombie": "ZombieFlag",
        "MaxNextWaveHealthPercentage": 0.15,
        "MinNextWaveHealthPercentage": 0.2,
        "SpawnColEnd": 20.0,
        "SpawnColStart": 5.0,
        "Wave": [
            {
                "Dynamic": {
                    "Point": 0,
                    "ZombiePool": []
                },
                "DynamicPlantfood": [
                    0,
                    0,
                    0,
                    0,
                    0,
                    0,
                    0
                ],
                "Event": [],
                "Spawn": [
                    {
                        "Line": 2,
                        "Num": 1,
                        "Zombie": "ZombieNormal"
                    },
                    {
                        "Line": 3,
                        "Num": 1,
                        "Zombie": "ZombieNormalPeaShooterSingle"
                    },
                    {
                        "Line": 4,
                        "Num": 1,
                        "Zombie": "ZombieNormal"
                    }
                ]
            },
            {
                "Dynamic": {
                    "Point": 800,
                    "ZombiePool": [
                        "ZombieNormalPeaShooter",
                        "ZombieNormalPeaShooter",
                        "ZombieNormalPeaShooterSingle",
                        "ZombieNormalPeaShooterSingle",
                        "ZombieNormalPeaShooterSingle"
                    ]
                },
                "DynamicPlantfood": [
                    0,
                    0,
                    0,
                    0,
                    0,
                    0,
                    0
                ],
                "Event": [],
                "Spawn": []
            },
            {
                "Dynamic": {
                    "Point": 1500,
                    "ZombiePool": [
                        "ZombieNormalWallnut",
                        "ZombieNormalWallnut",
                        "ZombieNormalWallnut",
                        "ZombieNormalPeaShooterSingle",
                        "ZombieNormalPeaShooterSingle"
                    ]
                },
                "DynamicPlantfood": [
                    0,
                    0,
                    0,
                    0,
                    0,
                    0,
                    0
                ],
                "Event": [],
                "Spawn": []
            },
            {
                "Dynamic": {
                    "Point": 1400,
                    "ZombiePool": [
                        "ZombieNormalLmitater",
                        "ZombieNormalLmitater",
                        "ZombieNormalLmitater",
                        "ZombieNormal",
                        "ZombieNormal"
                    ]
                },
                "DynamicPlantfood": [
                    0,
                    0,
                    0,
                    0,
                    0,
                    0,
                    0
                ],
                "Event": [],
                "Spawn": []
            },
            {
                "Dynamic": {
                    "Point": 1600,
                    "ZombiePool": [
                        "ZombieNormalLmitater",
                        "ZombieNormalLmitater",
                        "ZombieNormalLmitater",
                        "ZombieNormalCabbagepult",
                        "ZombieNormalCabbagepult"
                    ]
                },
                "DynamicPlantfood": [
                    0,
                    0,
                    0,
                    0,
                    0,
                    0,
                    0
                ],
                "Event": [],
                "Spawn": []
            },
            {
                "Dynamic": {
                    "Point": 600,
                    "ZombiePool": [
                        "ZombieSleeper",
                        "ZombieSleeper",
                        "ZombieSleeper"
                    ]
                },
                "DynamicPlantfood": [
                    0,
                    0,
                    0,
                    0,
                    0,
                    0,
                    0
                ],
                "Event": [],
                "Spawn": []
            },
            {
                "Dynamic": {
                    "Point": 2050,
                    "ZombiePool": [
                        "ZombieFootball",
                        "ZombieFootball",
                        "ZombieFootball",
                        "ZombieFootball",
                        "ZombieFootballFumeShroom"
                    ]
                },
                "DynamicPlantfood": [
                    0,
                    0,
                    0,
                    0,
                    0,
                    0,
                    0
                ],
                "Event": [],
                "Spawn": []
            },
            {
                "Dynamic": {
                    "Point": 1550,
                    "ZombiePool": [
                        "ZombieFootballBlack",
                        "ZombieFootballBlack",
                        "ZombieFootballBlackFumeShroom"
                    ]
                },
                "DynamicPlantfood": [
                    0,
                    0,
                    0,
                    0,
                    0,
                    0,
                    0
                ],
                "Event": [],
                "Spawn": []
            },
            {
                "Dynamic": {
                    "Point": 1000,
                    "ZombiePool": [
                        "ZombiePolestriker",
                        "ZombiePolestriker",
                        "ZombieJackbox"
                    ]
                },
                "DynamicPlantfood": [
                    0,
                    0,
                    0,
                    0,
                    0,
                    0,
                    0
                ],
                "Event": [],
                "Spawn": []
            },
            {
                "Dynamic": {
                    "Point": 1950,
                    "ZombiePool": [
                        "ZombieMagnetic",
                        "ZombieMagnetic",
                        "ZombieNormalIcenut",
                        "ZombieNormalIcenut",
                        "ZombieNormalIcenut"
                    ]
                },
                "DynamicPlantfood": [
                    0,
                    0,
                    0,
                    0,
                    0,
                    0,
                    0
                ],
                "Event": [
                    {
                        "EventName": "MapChange",
                        "Value": {
                            "Delay": 0.0,
                            "Duration": 10.0,
                            "MapName": "FrontlawnNightCold"
                        }
                    }
                ],
                "Spawn": []
            },
            {
                "Dynamic": {
                    "Point": 1800,
                    "ZombiePool": [
                        "ZombieNormalBucket",
                        "ZombieNormalBucket",
                        "ZombieNormalScreendoor",
                        "ZombieNormalScreendoor",
                        "ZombieNormalBucket",
                        "ZombieNormalScreendoor"
                    ]
                },
                "DynamicPlantfood": [
                    0,
                    0,
                    0,
                    0,
                    0,
                    0,
                    0
                ],
                "Event": [],
                "Spawn": []
            },
            {
                "Dynamic": {
                    "Point": 1000,
                    "ZombiePool": [
                        "ZombieNormalCone",
                        "ZombieNormalCone",
                        "ZombieNormalScreendoor",
                        "ZombieNormalScreendoor",
                        "ZombieNormalScreendoor"
                    ]
                },
                "DynamicPlantfood": [
                    0,
                    0,
                    0,
                    0,
                    0,
                    0,
                    0
                ],
                "Event": [],
                "Spawn": []
            },
            {
                "Dynamic": {
                    "Point": 1400,
                    "ZombiePool": [
                        "ZombieNormalScreendoor",
                        "ZombieNormalScreendoor",
                        "ZombieNormalWallnut",
                        "ZombieNormalWallnut",
                        "ZombieNormalScreendoor"
                    ]
                },
                "DynamicPlantfood": [
                    0,
                    0,
                    0,
                    0,
                    0,
                    0,
                    0
                ],
                "Event": [],
                "Spawn": []
            },
            {
                "Dynamic": {
                    "Point": 1200,
                    "ZombiePool": [
                        "ZombieNormalLmitater",
                        "ZombieNormalLmitater",
                        "ZombieNormalLmitater"
                    ]
                },
                "DynamicPlantfood": [
                    0,
                    0,
                    0,
                    0,
                    0,
                    0,
                    0
                ],
                "Event": [],
                "Spawn": []
            },
            {
                "Dynamic": {
                    "Point": 750,
                    "ZombiePool": [
                        "ZombieAxe",
                        "ZombieAxe",
                        "ZombieAxe"
                    ]
                },
                "DynamicPlantfood": [
                    0,
                    0,
                    0,
                    0,
                    0,
                    0,
                    0
                ],
                "Event": [],
                "Spawn": []
            },
            {
                "Dynamic": {
                    "Point": 2950,
                    "ZombiePool": [
                        "ZombieGargantuarZamboni",
                        "ZombieGargantuarZamboni",
                        "ZombiePaperball",
                        "ZombiePaperball",
                        "ZombiePaperball"
                    ]
                },
                "DynamicPlantfood": [
                    0,
                    0,
                    0,
                    0,
                    0,
                    0,
                    0
                ],
                "Event": [],
                "Spawn": []
            }
        ]
    }
}