{
    "Name": "IZM_Level22",
    "BGM": "Cerebraw",
    "Description": "PLAYERS_TRIP_TO_MODERN",
    "Event": {
        "EventInit": [
            {
                "EventName": "CurrentMapUseStripe",
                "Value": {
                    "Row": 7
                }
            }
        ],
        "EventReady": [],
        "EventStart": []
    },
    "FinishMethod": "IZM",
    "HomeWorld": "NOONE",
    "IZMManager": {
        "Shuffle": true
    },
    "LevelName": "僵尸封印",
    "LevelNumber": 22,
    "Map": "FrontlawnNight",
    "MowerUse": true,
    "PacketBank": {
        "ColdDownStart": true,
        "ColdDownUse": false,
        "LimitGridPlantNum": -1,
        "Method": "PRESET",
        "PlantColumn": false,
        "Type": "GeneralZombie",
        "Value": [
            {
                "PacketName": "ZombieNormal"
            },
            {
                "PacketName": "ZombiePolevaulter"
            },
            {
                "PacketName": "ZombieFootballBlack"
            },
            {
                "PacketName": "ZombieGargantuar"
            },
            {
                "PacketName": "ZombieGargantuarRedEyes"
            },
            {
                "PacketName": "ZombieGargantuarZamboni"
            }
        ]
    },
    "PreSpawn": {
        "Packet": [
            {
                "GridPos": [
                    1,
                    1
                ],
                "Name": "PlantWinterMelonShroom"
            },
            {
                "GridPos": [
                    1,
                    2
                ],
                "Name": "PlantGloompult"
            },
            {
                "GridPos": [
                    1,
                    3
                ],
                "Name": "PlantGloompult"
            },
            {
                "GridPos": [
                    1,
                    4
                ],
                "Name": "PlantSquashVase"
            },
            {
                "GridPos": [
                    1,
                    5
                ],
                "Name": "PlantGatlingPea"
            },
            {
                "GridPos": [
                    2,
                    1
                ],
                "Name": "PlantGatlingPea"
            },
            {
                "GridPos": [
                    2,
                    2
                ],
                "Name": "PlantSunShroom"
            },
            {
                "GridPos": [
                    2,
                    3
                ],
                "Name": "PlantWildPea"
            },
            {
                "GridPos": [
                    2,
                    4
                ],
                "Name": "PlantGatlingPea"
            },
            {
                "GridPos": [
                    2,
                    5
                ],
                "Name": "PlantWinterMelonShroom"
            },
            {
                "GridPos": [
                    3,
                    1
                ],
                "Name": "PlantSquashVase"
            },
            {
                "GridPos": [
                    3,
                    2
                ],
                "Name": "PlantWallnutABC_B"
            },
            {
                "GridPos": [
                    3,
                    3
                ],
                "Name": "PlantSquashVase"
            },
            {
                "GridPos": [
                    3,
                    4
                ],
                "Name": "PlantWildPea"
            },
            {
                "GridPos": [
                    3,
                    5
                ],
                "Name": "PlantDisguiserSunFlower"
            },
            {
                "GridPos": [
                    4,
                    1
                ],
                "Name": "PlantDisguiserSunFlower"
            },
            {
                "GridPos": [
                    4,
                    2
                ],
                "Name": "PlantSquashVase"
            },
            {
                "GridPos": [
                    4,
                    3
                ],
                "Name": "PlantDisguiserSunFlower"
            },
            {
                "GridPos": [
                    4,
                    4
                ],
                "Name": "PlantWallnutABC_B"
            },
            {
                "GridPos": [
                    4,
                    5
                ],
                "Name": "PlantGatlingPea"
            },
            {
                "GridPos": [
                    5,
                    1
                ],
                "Name": "PlantDisguiserSunFlower"
            },
            {
                "GridPos": [
                    5,
                    2
                ],
                "Name": "PlantWinterMelonShroom"
            },
            {
                "GridPos": [
                    5,
                    3
                ],
                "Name": "PlantSunShroom"
            },
            {
                "GridPos": [
                    5,
                    4
                ],
                "Name": "PlantDisguiserSunFlower"
            },
            {
                "GridPos": [
                    5,
                    5
                ],
                "Name": "PlantDisguiserSunFlower"
            },
            {
                "GridPos": [
                    6,
                    1
                ],
                "Name": "PlantSunShroom"
            },
            {
                "GridPos": [
                    6,
                    2
                ],
                "Name": "PlantSquashVase"
            },
            {
                "GridPos": [
                    6,
                    3
                ],
                "Name": "PlantSquashVase"
            },
            {
                "GridPos": [
                    6,
                    4
                ],
                "Name": "PlantSunShroom"
            },
            {
                "GridPos": [
                    6,
                    5
                ],
                "Name": "PlantSquashVase"
            },
            {
                "GridPos": [
                    7,
                    1
                ],
                "Name": "PlantSquashVase"
            },
            {
                "GridPos": [
                    7,
                    2
                ],
                "Name": "PlantDisguiserSunFlower"
            },
            {
                "GridPos": [
                    7,
                    3
                ],
                "Name": "PlantSunShroom"
            },
            {
                "GridPos": [
                    7,
                    4
                ],
                "Name": "PlantSquashVase"
            },
            {
                "GridPos": [
                    7,
                    5
                ],
                "Name": "PlantSunShroom"
            }
        ]
    },
    "Reward": {
        "RewardFirst": 2000,
        "RewardType": "COIN"
    },
    "SunManager": {
        "Begin": 1200,
        "MovingMethod": "LAND",
        "Open": true,
        "SpawnInterval": 12.0,
        "SpawnNum": 50
    },
    "Talk": "",
    "Tutorial": ""
}