{
	"Name": "Challenge_Level16_3",
	"Description": "PLAYERS_TRIP_TO_MODERN",
	"LevelName": "CHALLENGE_LEVEL_NAME_16",
	"LevelNumber": 3,
	"NextLevel": "",
	"HomeWorld": "Morden",
	"Talk": "",
	"Tutorial": "",
	"Map": "FrontlawnNightCold",
	"BGM": "FrontlawnNight",
	"Reward": {
		"RewardFirst": "PlantIceCobCannon",
		"RewardType": "Packet"
	},
	"Event": {
		"EventInit": [],
		"EventReady": [],
		"EventStart": []
	},
	"PreSpawn": {
		"Packet": []
	},
	"PacketBank": {
		"Method": "Choose",
		"Type": "GeneralPlant",
		"Value": [
			"PlantIceCobCannon"
		]
	},
	"SunManager": {
		"Begin": 500,
		"MovingMethod": "Land",
		"Open": false,
		"SpawnInterval": 12,
		"SpawnNum": 50
	},
	"WaveManager": {
		"BeginCol": 20,
		"Dynamic": [
			{},
			{},
			{},
			{},
			{},
			{},
			{}
		],
		"FlagWaveInterval": 4,
		"FlagZombie": "ZombieFlag",
		"MaxNextWaveHealthPercentage": 0.27,
		"MinNextWaveHealthPercentage": 0.15,
		"SpawnColEnd": 30,
		"SpawnColStart": 26,
		"SpawnOverride": {},
		"Wave": [
			{
				"Event": [],
				"DynamicPlantfood": [
					0,
					0,
					0,
					0,
					0,
					0,
					0
				],
				"Spawn": [
					{
						"Line": -1,
						"Num": 2,
						"Override": {
							"Invisible": true
						},
						"Zombie": "ZombieNormal"
					},
					{
						"Line": -1,
						"Num": 2,
						"Override": {
							"Invisible": true
						},
						"Zombie": "ZombieYetiDigger"
					}
				]
			},
			{
				"Event": [],
				"DynamicPlantfood": [
					0,
					0,
					0,
					0,
					0,
					0,
					0
				],
				"Spawn": [
					{
						"Line": -1,
						"Num": 2,
						"Override": {
							"Invisible": true
						},
						"Zombie": "ZombieNormalCone"
					},
					{
						"Line": -1,
						"Num": 2,
						"Override": {
							"Invisible": true
						},
						"Zombie": "ZombieYetiDigger"
					},
					{
						"Line": -1,
						"Num": 3,
						"Override": {
							"Invisible": true
						},
						"Zombie": "ZombieNormalGatlingPea"
					}
				]
			},
			{
				"Event": [],
				"DynamicPlantfood": [
					0,
					0,
					0,
					0,
					0,
					0,
					0
				],
				"Spawn": [
					{
						"Line": -1,
						"Num": 1,
						"Override": {
							"Invisible": true
						},
						"Zombie": "ZombieSleeper"
					},
					{
						"Line": -1,
						"Num": 3,
						"Override": {
							"Invisible": true
						},
						"Zombie": "ZombieNormalCone"
					},
					{
						"Line": -1,
						"Num": 1,
						"Override": {
							"Invisible": true
						},
						"Zombie": "ZombieYetiDigger"
					},
					{
						"Line": -1,
						"Num": 1,
						"Override": {
							"Invisible": true
						},
						"Zombie": "ZombieNormalGatlingPea"
					}
				]
			},
			{
				"Event": [],
				"DynamicPlantfood": [
					0,
					0,
					0,
					0,
					0,
					0,
					0
				],
				"Spawn": [
					{
						"Line": -1,
						"Num": 3,
						"Override": {
							"Invisible": true
						},
						"Zombie": "ZombieNormal"
					},
					{
						"Line": -1,
						"Num": 3,
						"Override": {
							"Invisible": true
						},
						"Zombie": "ZombieNormalCone"
					},
					{
						"Line": -1,
						"Num": 2,
						"Override": {
							"Invisible": true
						},
						"Zombie": "ZombieAxe"
					},
					{
						"Line": -1,
						"Num": 3,
						"Override": {
							"Invisible": true
						},
						"Zombie": "ZombieBungiBin"
					},
					{
						"Line": -1,
						"Num": 2,
						"Override": {
							"Invisible": true
						},
						"Zombie": "ZombieYetiDigger"
					}
				]
			},
			{
				"Event": [],
				"DynamicPlantfood": [
					0,
					0,
					0,
					0,
					0,
					0,
					0
				],
				"Spawn": [
					{
						"Line": -1,
						"Num": 2,
						"Override": {
							"Invisible": true
						},
						"Zombie": "ZombieSleeper"
					},
					{
						"Line": -1,
						"Num": 1,
						"Override": {
							"Invisible": true
						},
						"Zombie": "ZombieAxe"
					},
					{
						"Line": -1,
						"Num": 2,
						"Override": {
							"Invisible": true
						},
						"Zombie": "ZombieNormalGatlingPea"
					},
					{
						"Line": -1,
						"Num": 2,
						"Override": {
							"Invisible": true
						},
						"Zombie": "ZombieNormalCone"
					}
				]
			},
			{
				"Event": [],
				"DynamicPlantfood": [
					0,
					0,
					0,
					0,
					0,
					0,
					0
				],
				"Spawn": [
					{
						"Line": -1,
						"Num": 1,
						"Override": {
							"Invisible": true
						},
						"Zombie": "ZombieDiscopaper"
					},
					{
						"Line": -1,
						"Num": 2,
						"Override": {
							"Invisible": true
						},
						"Zombie": "ZombieNormalCone"
					},
					{
						"Line": -1,
						"Num": 2,
						"Override": {
							"Invisible": true
						},
						"Zombie": "ZombieAxe"
					},
					{
						"Line": -1,
						"Num": 2,
						"Override": {
							"Invisible": true
						},
						"Zombie": "ZombieYetiDigger"
					},
					{
						"Line": -1,
						"Num": 3,
						"Override": {
							"Invisible": true
						},
						"Zombie": "ZombieNormal"
					}
				]
			},
			{
				"Event": [],
				"DynamicPlantfood": [
					0,
					0,
					0,
					0,
					0,
					0,
					0
				],
				"Spawn": [
					{
						"Line": -1,
						"Num": 2,
						"Override": {
							"Invisible": true
						},
						"Zombie": "ZombieNormalCone"
					},
					{
						"Line": -1,
						"Num": 4,
						"Override": {
							"Invisible": true
						},
						"Zombie": "ZombieNormal"
					},
					{
						"Line": -1,
						"Num": 2,
						"Override": {
							"Invisible": true
						},
						"Zombie": "ZombieNormalGatlingPea"
					},
					{
						"Line": -1,
						"Num": 5,
						"Override": {
							"Invisible": true
						},
						"Zombie": "ZombieAxe"
					},
					{
						"Line": -1,
						"Num": 1,
						"Override": {
							"Invisible": true
						},
						"Zombie": "ZombieYetiDigger"
					}
				]
			},
			{
				"Event": [],
				"DynamicPlantfood": [
					0,
					0,
					0,
					0,
					0,
					0,
					0
				],
				"Spawn": [
					{
						"Line": -1,
						"Num": 4,
						"Override": {
							"Invisible": true
						},
						"Zombie": "ZombieNormal"
					},
					{
						"Line": -1,
						"Num": 1,
						"Override": {
							"Invisible": true
						},
						"Zombie": "ZombieDiscopaper"
					},
					{
						"Line": -1,
						"Num": 2,
						"Override": {
							"Invisible": true
						},
						"Zombie": "ZombiePaperball"
					},
					{
						"Line": -1,
						"Num": 4,
						"Override": {
							"Invisible": true
						},
						"Zombie": "ZombieNormalGatlingPea"
					},
					{
						"Line": -1,
						"Num": 4,
						"Override": {
							"Invisible": true
						},
						"Zombie": "ZombieNormalGatlingPea"
					},
					{
						"Line": -1,
						"Num": 2,
						"Override": {
							"Invisible": true
						},
						"Zombie": "ZombieZambonipult"
					},
					{
						"Line": -1,
						"Num": 5,
						"Override": {
							"Invisible": true
						},
						"Zombie": "ZombieBungiBin"
					}
				]
			},
			{
				"Event": [],
				"DynamicPlantfood": [
					0,
					0,
					0,
					0,
					0,
					0,
					0
				],
				"Spawn": [
					{
						"Line": -1,
						"Num": 4,
						"Override": {
							"Invisible": true
						},
						"Zombie": "ZombieAxe"
					},
					{
						"Line": -1,
						"Num": 2,
						"Override": {
							"Invisible": true
						},
						"Zombie": "ZombiePaperball"
					},
					{
						"Line": -1,
						"Num": 4,
						"Override": {
							"Invisible": true
						},
						"Zombie": "ZombieNormalGatlingPea"
					},
					{
						"Line": -1,
						"Num": 4,
						"Override": {
							"Invisible": true
						},
						"Zombie": "ZombiePortal"
					},
					{
						"Line": -1,
						"Num": 3,
						"Override": {
							"Invisible": true
						},
						"Zombie": "ZombieBungiBin"
					},
					{
						"Line": -1,
						"Num": 2,
						"Override": {
							"Invisible": true
						},
						"Zombie": "ZombiePaperball"
					},
					{
						"Line": -1,
						"Num": 1,
						"Override": {
							"Invisible": true
						},
						"Zombie": "ZombieZambonipult"
					},
					{
						"Line": -1,
						"Num": 1,
						"Override": {
							"Invisible": true
						},
						"Zombie": "ZombieYetiDigger"
					}
				]
			},
			{
				"Event": [],
				"DynamicPlantfood": [
					0,
					0,
					0,
					0,
					0,
					0,
					0
				],
				"Spawn": [
					{
						"Line": -1,
						"Num": 3,
						"Override": {
							"Invisible": true
						},
						"Zombie": "ZombiePortal"
					},
					{
						"Line": -1,
						"Num": 7,
						"Override": {
							"Invisible": true
						},
						"Zombie": "ZombieAxe"
					},
					{
						"Line": -1,
						"Num": 2,
						"Override": {
							"Invisible": true
						},
						"Zombie": "ZombieDiscopaper"
					},
					{
						"Line": -1,
						"Num": 2,
						"Override": {
							"Invisible": true
						},
						"Zombie": "ZombieSleeper"
					},
					{
						"Line": -1,
						"Num": 1,
						"Override": {
							"Invisible": true
						},
						"Zombie": "ZombieZambonipult"
					},
					{
						"Line": -1,
						"Num": 3,
						"Override": {
							"Invisible": true
						},
						"Zombie": "ZombieYetiDigger"
					},
					{
						"Line": -1,
						"Num": 5,
						"Override": {
							"Invisible": true
						},
						"Zombie": "ZombieBungiBin"
					},
					{
						"Line": -1,
						"Num": 5,
						"Override": {
							"Invisible": true
						},
						"Zombie": "ZombieNormalGatlingPea"
					}
				]
			},
			{
				"Event": [],
				"DynamicPlantfood": [
					0,
					0,
					0,
					0,
					0,
					0,
					0
				],
				"Spawn": [
					{
						"Line": -1,
						"Num": 2,
						"Override": {
							"Invisible": true
						},
						"Zombie": "ZombieSleeper"
					},
					{
						"Line": -1,
						"Num": 3,
						"Override": {
							"Invisible": true
						},
						"Zombie": "ZombieZambonipult"
					},
					{
						"Line": -1,
						"Num": 1,
						"Override": {
							"Invisible": true
						},
						"Zombie": "ZombieDiscopaper"
					},
					{
						"Line": -1,
						"Num": 2,
						"Override": {
							"Invisible": true
						},
						"Zombie": "ZombieNormalGatlingPea"
					},
					{
						"Line": -1,
						"Num": 3,
						"Override": {
							"Invisible": true
						},
						"Zombie": "ZombiePaperball"
					},
					{
						"Line": -1,
						"Num": 8,
						"Override": {
							"Invisible": true
						},
						"Zombie": "ZombieBungiBin"
					},
					{
						"Line": -1,
						"Num": 3,
						"Override": {
							"Invisible": true
						},
						"Zombie": "ZombiePortal"
					},
					{
						"Line": -1,
						"Num": 5,
						"Override": {
							"Invisible": true
						},
						"Zombie": "ZombieYetiDigger"
					},
					{
						"Line": -1,
						"Num": 6,
						"Override": {
							"Invisible": true
						},
						"Zombie": "ZombieAxe"
					}
				]
			},
			{
				"Event": [],
				"DynamicPlantfood": [
					0,
					0,
					0,
					0,
					0,
					0,
					0
				],
				"Spawn": [
					{
						"Line": -1,
						"Num": 4,
						"Override": {
							"Invisible": true
						},
						"Zombie": "ZombiePaperball"
					},
					{
						"Line": -1,
						"Num": 3,
						"Override": {
							"Invisible": true
						},
						"Zombie": "ZombieDiscopaper"
					},
					{
						"Line": -1,
						"Num": 3,
						"Override": {
							"Invisible": true
						},
						"Zombie": "ZombieZambonipult"
					},
					{
						"Line": -1,
						"Num": 4,
						"Override": {
							"Invisible": true
						},
						"Zombie": "ZombiePortal"
					},
					{
						"Line": -1,
						"Num": 10,
						"Override": {
							"Invisible": true
						},
						"Zombie": "ZombieBungiBin"
					},
					{
						"Line": -1,
						"Num": 5,
						"Override": {
							"Invisible": true
						},
						"Zombie": "ZombieSleeper"
					},
					{
						"Line": -1,
						"Num": 10,
						"Override": {
							"Invisible": true
						},
						"Zombie": "ZombieAxe"
					},
					{
						"Line": -1,
						"Num": 10,
						"Override": {
							"Invisible": true
						},
						"Zombie": "ZombieNormalGatlingPea"
					},
					{
						"Line": -1,
						"Num": 8,
						"Override": {
							"Invisible": true
						},
						"Zombie": "ZombieYetiDigger"
					}
				]
			}
		]
	}
}