{
	"Name": "Vase_Level14",
	"BGM": "Cerebraw",
	"Description": "PLAYERS_TRIP_TO_MODERN",
	"Event": {
		"EventInit": [],
		"EventReady": [],
		"EventStart": []
	},
	"FinishMethod": "VASE",
	"HomeWorld": "NOONE",
	"LevelName": "绝对零度",
	"LevelNumber": 14.0,
	"Map": "FrontlawnNightCold",
	"MowerUse": false,
	"PacketBank": {
		"ColdDownStart": false,
		"LimitGridPlantNum": -1.0,
		"Method": "NOONE",
		"PlantColumn": false,
		"Type": "GeneralPlant",
		"Value": [
			{
				"PacketName": "PlantWinterMelonShroom"
			},
			{
				"PacketName": "PlantGloompult"
			},
			{
				"PacketName": "PlantIcenut"
			}
		]
	},
	"PreSpawn": {
		"Packet": []
	},
	"Reward": {
		"RewardFirst": 2000.0,
		"RewardType": "COIN"
	},
	"SunManager": {
		"Begin": 0.0,
		"MovingMethod": "LAND",
		"Open": false,
		"SpawnInterval": 12.0,
		"SpawnNum": 50.0
	},
	"Talk": "",
	"Tutorial": "",
	"VaseManager": {
		"Shuffle": true,
		"Vase": [
			{
				"GridPos": [
					3.0,
					1.0
				],
				"PacketName": "PlantIcenutBowling",
				"Type": "Normal"
			},
			{
				"GridPos": [
					3.0,
					2.0
				],
				"PacketName": "ZombieJackson",
				"Type": "Normal"
			},
			{
				"GridPos": [
					3.0,
					3.0
				],
				"PacketName": "PlantIcenutBowling",
				"Type": "Normal"
			},
			{
				"GridPos": [
					3.0,
					4.0
				],
				"PacketName": "PlantIcenutBowling",
				"Type": "Normal"
			},
			{
				"GridPos": [
					3.0,
					5.0
				],
				"PacketName": "PlantIcenutBowling",
				"Type": "Normal"
			},
			{
				"GridPos": [
					4.0,
					1.0
				],
				"PacketName": "ZombiePolevaulter",
				"Type": "Normal"
			},
			{
				"GridPos": [
					4.0,
					2.0
				],
				"PacketName": "PlantIcenutBowling",
				"Type": "Normal"
			},
			{
				"GridPos": [
					4.0,
					3.0
				],
				"PacketName": "ZombieDisco",
				"Type": "Normal"
			},
			{
				"GridPos": [
					4.0,
					4.0
				],
				"PacketName": "PlantIcenutBowling",
				"Type": "Normal"
			},
			{
				"GridPos": [
					4.0,
					5.0
				],
				"PacketName": "ZombieJackbox",
				"Type": "Normal"
			},
			{
				"GridPos": [
					5.0,
					1.0
				],
				"PacketName": "ZombiePolevaulter",
				"Type": "Normal"
			},
			{
				"GridPos": [
					5.0,
					2.0
				],
				"PacketName": "PlantSnowShroom",
				"Type": "Normal"
			},
			{
				"GridPos": [
					5.0,
					3.0
				],
				"PacketName": "ZombiePaper",
				"Type": "Normal"
			},
			{
				"GridPos": [
					5.0,
					4.0
				],
				"PacketName": "ZombieNormalScreendoor",
				"Type": "Normal"
			},
			{
				"GridPos": [
					5.0,
					5.0
				],
				"PacketName": "ZombiePaper",
				"Type": "Normal"
			},
			{
				"GridPos": [
					6.0,
					1.0
				],
				"PacketName": "ZombieNormalScreendoor",
				"Type": "Normal"
			},
			{
				"GridPos": [
					6.0,
					2.0
				],
				"PacketName": "ZombieJacksonHelmet",
				"Type": "Normal"
			},
			{
				"GridPos": [
					6.0,
					3.0
				],
				"PacketName": "PlantIcenutBowling",
				"Type": "Normal"
			},
			{
				"GridPos": [
					6.0,
					4.0
				],
				"PacketName": "ZombiePaper",
				"Type": "Normal"
			},
			{
				"GridPos": [
					6.0,
					5.0
				],
				"PacketName": "PlantIcenutBowling",
				"Type": "Normal"
			},
			{
				"GridPos": [
					7.0,
					1.0
				],
				"PacketName": "ZombiePolevaulter",
				"Type": "Normal"
			},
			{
				"GridPos": [
					7.0,
					2.0
				],
				"PacketName": "ZombiePaper",
				"Type": "Normal"
			},
			{
				"GridPos": [
					7.0,
					3.0
				],
				"PacketName": "ZombieJacksonHelmet",
				"Type": "Normal"
			},
			{
				"GridPos": [
					7.0,
					4.0
				],
				"PacketName": "PlantIcenutBowling",
				"Type": "Normal"
			},
			{
				"GridPos": [
					7.0,
					5.0
				],
				"PacketName": "ZombieDisco",
				"Type": "Normal"
			},
			{
				"GridPos": [
					8.0,
					1.0
				],
				"PacketName": "ZombiePolevaulter",
				"Type": "Normal"
			},
			{
				"GridPos": [
					8.0,
					2.0
				],
				"PacketName": "PlantIcenutBowling",
				"Type": "Normal"
			},
			{
				"GridPos": [
					8.0,
					3.0
				],
				"PacketName": "ZombieNormalScreendoor",
				"Type": "Normal"
			},
			{
				"GridPos": [
					8.0,
					4.0
				],
				"PacketName": "ZombieNormalScreendoor",
				"Type": "Normal"
			},
			{
				"GridPos": [
					8.0,
					5.0
				],
				"PacketName": "ZombieDisco",
				"Type": "Normal"
			},
			{
				"GridPos": [
					9.0,
					1.0
				],
				"PacketName": "ZombieNormalScreendoor",
				"Type": "Normal"
			},
			{
				"GridPos": [
					9.0,
					2.0
				],
				"PacketName": "ZombiePolevaulter",
				"Type": "Normal"
			},
			{
				"GridPos": [
					9.0,
					3.0
				],
				"PacketName": "ZombieJackson",
				"Type": "Normal"
			},
			{
				"GridPos": [
					9.0,
					4.0
				],
				"PacketName": "ZombieJacksonX",
				"Type": "Normal"
			},
			{
				"GridPos": [
					9.0,
					5.0
				],
				"PacketName": "PlantIcenutBowling",
				"Type": "Normal"
			}
		],
		"VaseFill": []
	}
}
