{
	"Name": "Vase_Level11",
	"BGM": "Cerebraw",
	"Description": "PLAYERS_TRIP_TO_MODERN",
	"Event": {
		"EventInit": [],
		"EventReady": [],
		"EventStart": []
	},
	"FinishMethod": "VASE",
	"HomeWorld": "NOONE",
	"LevelName": "水陆互通",
	"LevelNumber": 11.0,
	"Map": "BackyardNight",
	"MowerUse": false,
	"PacketBank": {
		"ColdDownStart": true,
		"LimitGridPlantNum": -1.0,
		"Method": "NOONE",
		"PlantColumn": false,
		"Type": "GeneralPlant",
		"Value": []
	},
	"PreSpawn": {
		"Packet": []
	},
	"Reward": {
		"RewardFirst": 2000.0,
		"RewardType": "COIN"
	},
	"SunManager": {
		"Begin": 300.0,
		"MovingMethod": "LAND",
		"Open": false,
		"SpawnInterval": 12.0,
		"SpawnNum": 50.0
	},
	"Talk": "",
	"Tutorial": "",
	"VaseManager": {
		"Shuffle": true,
		"Vase": [
			{
				"GridPos": [
					3.0,
					1.0
				],
				"PacketName": "PlantPeaCat",
				"Type": "Normal"
			},
			{
				"GridPos": [
					3.0,
					2.0
				],
				"PacketName": "PlantPeaPot",
				"Type": "Normal"
			},
			{
				"GridPos": [
					3.0,
					3.0
				],
				"PacketName": "ZombieDolphinrider",
				"Type": "Zombie"
			},
			{
				"GridPos": [
					3.0,
					4.0
				],
				"PacketName": "ZombiePolevaulter",
				"Type": "Normal"
			},
			{
				"GridPos": [
					3.0,
					5.0
				],
				"PacketName": "PlantSeaNut",
				"Type": "Normal"
			},
			{
				"GridPos": [
					3.0,
					6.0
				],
				"PacketName": "PlantSquash",
				"Type": "Normal"
			},
			{
				"GridPos": [
					4.0,
					1.0
				],
				"PacketName": "ZombiePolevaulter",
				"Type": "Normal"
			},
			{
				"GridPos": [
					4.0,
					2.0
				],
				"PacketName": "PlantFirenut",
				"Type": "Normal"
			},
			{
				"GridPos": [
					4.0,
					3.0
				],
				"PacketName": "ZombieDolphinrider",
				"Type": "Zombie"
			},
			{
				"GridPos": [
					4.0,
					4.0
				],
				"PacketName": "ZombiePolevaulter",
				"Type": "Normal"
			},
			{
				"GridPos": [
					4.0,
					5.0
				],
				"PacketName": "PlantPeaWell",
				"Type": "Normal"
			},
			{
				"GridPos": [
					4.0,
					6.0
				],
				"PacketName": "ZombieDolphinrider",
				"Type": "Normal"
			},
			{
				"GridPos": [
					5.0,
					1.0
				],
				"PacketName": "ZombieFootballBlack",
				"Type": "Normal"
			},
			{
				"GridPos": [
					5.0,
					2.0
				],
				"PacketName": "PlantSnowwood",
				"Type": "Normal"
			},
			{
				"GridPos": [
					5.0,
					3.0
				],
				"PacketName": "PlantSeaNut",
				"Type": "Normal"
			},
			{
				"GridPos": [
					5.0,
					4.0
				],
				"PacketName": "ZombieSnorkle",
				"Type": "Zombie"
			},
			{
				"GridPos": [
					5.0,
					5.0
				],
				"PacketName": "ZombieDolphinrider",
				"Type": "Normal"
			},
			{
				"GridPos": [
					5.0,
					6.0
				],
				"PacketName": "ZombieDuck",
				"Type": "Normal"
			},
			{
				"GridPos": [
					6.0,
					1.0
				],
				"PacketName": "ZombieSnorkle",
				"Type": "Normal"
			},
			{
				"GridPos": [
					6.0,
					2.0
				],
				"PacketName": "PlantPeaWell",
				"Type": "Normal"
			},
			{
				"GridPos": [
					6.0,
					3.0
				],
				"PacketName": "PlantPuffPot",
				"Type": "Normal"
			},
			{
				"GridPos": [
					6.0,
					4.0
				],
				"PacketName": "ZombieSnorkle",
				"Type": "Zombie"
			},
			{
				"GridPos": [
					6.0,
					5.0
				],
				"PacketName": "ZombiePolevaulter",
				"Type": "Normal"
			},
			{
				"GridPos": [
					6.0,
					6.0
				],
				"PacketName": "PlantPeaLilyPad",
				"Type": "Normal"
			},
			{
				"GridPos": [
					7.0,
					1.0
				],
				"PacketName": "PlantSquash",
				"Type": "Normal"
			},
			{
				"GridPos": [
					7.0,
					2.0
				],
				"PacketName": "ZombieFootball",
				"Type": "Normal"
			},
			{
				"GridPos": [
					7.0,
					3.0
				],
				"PacketName": "ZombieShadow",
				"Type": "Plant"
			},
			{
				"GridPos": [
					7.0,
					4.0
				],
				"PacketName": "ZombieDuckCone",
				"Type": "Normal"
			},
			{
				"GridPos": [
					7.0,
					5.0
				],
				"PacketName": "PlantFirenut",
				"Type": "Normal"
			},
			{
				"GridPos": [
					7.0,
					6.0
				],
				"PacketName": "PlantSnowwood",
				"Type": "Normal"
			},
			{
				"GridPos": [
					8.0,
					1.0
				],
				"PacketName": "PlantPeaCat",
				"Type": "Normal"
			},
			{
				"GridPos": [
					8.0,
					2.0
				],
				"PacketName": "PlantPeaLilyPad",
				"Type": "Normal"
			},
			{
				"GridPos": [
					8.0,
					3.0
				],
				"PacketName": "ZombieDuckCone",
				"Type": "Normal"
			},
			{
				"GridPos": [
					8.0,
					4.0
				],
				"PacketName": "ZombieFootball",
				"Type": "Normal"
			},
			{
				"GridPos": [
					8.0,
					5.0
				],
				"PacketName": "ZombieNormal",
				"Type": "Normal"
			},
			{
				"GridPos": [
					8.0,
					6.0
				],
				"PacketName": "PlantPeaCat",
				"Type": "Normal"
			},
			{
				"GridPos": [
					9.0,
					1.0
				],
				"PacketName": "ZombieNormalCone",
				"Type": "Normal"
			},
			{
				"GridPos": [
					9.0,
					2.0
				],
				"PacketName": "ZombieSnorkle",
				"Type": "Normal"
			},
			{
				"GridPos": [
					9.0,
					3.0
				],
				"PacketName": "ZombieNormalBucket",
				"Type": "Normal"
			},
			{
				"GridPos": [
					9.0,
					4.0
				],
				"PacketName": "ZombieShadow",
				"Type": "Plant"
			},
			{
				"GridPos": [
					9.0,
					5.0
				],
				"PacketName": "PlantPeaWell",
				"Type": "Normal"
			},
			{
				"GridPos": [
					9.0,
					6.0
				],
				"PacketName": "ZombieDuck",
				"Type": "Normal"
			}
		],
		"VaseFill": []
	}
}
